[
  {
    "id": "3396632579",
    "title": "ITOps/InfoSec/DevOps Software Onboarding Process",
    "status": "current",
    "version": 8,
    "created": "2026-01-15T19:08:11.146Z",
    "ancestors": [
      {
        "id": "3482550638",
        "title": "Information Security Home"
      }
    ],
    "labels": [],
    "url": "https://oncologyanalytics.atlassian.net/wiki/spaces/IS/pages/3396632579/ITOps+InfoSec+DevOps+Software+Onboarding+Process"
  },
  {
    "id": "3398762497",
    "title": "Service Provider Onboarding Procedure",
    "status": "current",
    "version": 1,
    "created": "2024-05-06T16:23:57.731Z",
    "ancestors": [
      {
        "id": "3482550638",
        "title": "Information Security Home"
      }
    ],
    "labels": [],
    "url": "https://oncologyanalytics.atlassian.net/wiki/spaces/IS/pages/3398762497/Service+Provider+Onboarding+Procedure"
  },
  {
    "id": "3482550638",
    "title": "Information Security Home",
    "status": "current",
    "version": 3,
    "created": "2024-05-06T16:42:27.442Z",
    "ancestors": [],
    "labels": [],
    "url": "https://oncologyanalytics.atlassian.net/wiki/spaces/IS/overview"
  },
  {
    "id": "4485971969",
    "title": "🔐 Authorized Locations for Storing Protected Health Information (PHI)",
    "status": "current",
    "version": 6,
    "created": "2025-07-22T20:58:40.617Z",
    "ancestors": [
      {
        "id": "3482550638",
        "title": "Information Security Home"
      }
    ],
    "labels": [],
    "url": "https://oncologyanalytics.atlassian.net/wiki/spaces/IS/pages/4485971969/Authorized+Locations+for+Storing+Protected+Health+Information+PHI"
  }
]